<?xml version="1.0" encoding="UTF-8"?>
<basisgeo:FeatureCollectionGeometrie xmlns:basisgeo="http://www.geostandaarden.nl/basisgeometrie/1.0"
                                     xmlns:gml="http://www.opengis.net/gml/3.2">
   <basisgeo:featureMember>
      <basisgeo:Geometrie xmlns:geo="https://standaarden.overheid.nl/stop/imop/geo/"
                          xmlns:gio="https://standaarden.overheid.nl/stop/imop/gio/"
                          gml:id="id-741296bc-b7e4-4cc4-9c8f-c7064c1c47e4-xx">
         <basisgeo:id>741296bc-b7e4-4cc4-9c8f-c7064c1c47e4</basisgeo:id>
         <basisgeo:geometrie>
            <gml:Polygon srsName="urn:ogc:def:crs:EPSG::28992"
                         gml:id="id-741296bc-b7e4-4cc4-9c8f-c7064c1c47e4">
               <gml:exterior>
                  <gml:LinearRing>
                     <gml:posList>111374.206 550872.264 111373.286 550872.577 111372.208
                                    550872.944 111372.782 550874.597 111372.98 550874.528 111372.792
                                    550873.987 111372.47 550873.06 111374.242 550872.456 111374.525
                                    550873.27 111374.753 550873.926 111374.937 550873.862 111374.363
                                    550872.211 111374.206 550872.264</gml:posList>
                  </gml:LinearRing>
               </gml:exterior>
            </gml:Polygon>
         </basisgeo:geometrie>
      </basisgeo:Geometrie>
   </basisgeo:featureMember>
</basisgeo:FeatureCollectionGeometrie>
