<?xml version="1.0" encoding="UTF-8"?>
<basisgeo:FeatureCollectionGeometrie xmlns:basisgeo="http://www.geostandaarden.nl/basisgeometrie/1.0"
                                     xmlns:gml="http://www.opengis.net/gml/3.2">
   <basisgeo:featureMember>
      <basisgeo:Geometrie xmlns:geo="https://standaarden.overheid.nl/stop/imop/geo/"
                          xmlns:gio="https://standaarden.overheid.nl/stop/imop/gio/"
                          gml:id="id-86c2d387-d81b-4874-bd98-24020e66d2d0-xx">
         <basisgeo:id>86c2d387-d81b-4874-bd98-24020e66d2d0</basisgeo:id>
         <basisgeo:geometrie>
            <gml:MultiSurface srsName="urn:ogc:def:crs:EPSG::28992"
                              gml:id="id-86c2d387-d81b-4874-bd98-24020e66d2d0">
               <gml:surfaceMember>
                  <gml:Polygon>
                     <gml:exterior>
                        <gml:LinearRing>
                           <gml:posList>121103.258 530390.734 121103.226 530391.273 121102.091 530392.379 121101.723 530392.791 121098.784 530396.083 121096.745 530397.375 121094.815 530398.597 121091.111 530399.788 121085.695 530398.963 121083.879 530398.686 121081.996 530397.183 121079.559 530395.237 121074.068 530390.853 121069.058 530386.853 121063.058 530382.063 121048.007 530370.045 121034.947 530359.802 121021.904 530349.574 121019.793 530347.876 121018.367 530346.729 121016.132 530344.931 121011.584 530341.272 121001.254 530332.963 121000.0 530331.954 120997.385 530329.851 120996.989 530329.533 120996.304 530328.981 120994.789 530327.762 120991.336 530324.984 120977.767 530314.57 120976.495 530313.594 120974.363 530311.958 120970.258 530308.807 120964.236 530304.185 120950.777 530293.288 120941.39 530285.687 120940.158 530284.732 120929.267 530275.895 120917.265 530266.155 120906.788 530258.032 120901.86 530254.211 120900.21 530252.932 120890.398 530245.325 120885.186 530241.284 120853.732 530216.325 120847.003 530210.972 120824.7 530193.231 120799.592 530172.51 120795.814 530169.392 120762.212 530142.871 120748.984 530132.511 120735.323 530121.812 120713.363 530104.811 120702.139 530096.121 120672.244 530071.826 120672.233 530071.817 120672.202 530071.793 120665.01 530066.364 120659.617 530062.294 120653.464 530056.956 120653.445 530056.94 120653.419 530056.918 120648.762 530053.189 120647.943 530052.533 120643.133 530047.388 120639.367 530041.624 120636.71 530035.975 120635.872 530033.313 120635.609 530032.479 120635.024 530030.624 120634.494 530028.008 120634.176 530026.437 120633.984 530025.49 120633.973 530025.437 120633.88 530023.477 120633.807 530021.948 120633.796 530021.712 120633.784 530021.477 120633.935 530019.231 120634.09 530016.953 120634.742 530012.678 120634.97 530011.956 120635.494 530010.291 120636.25 530007.886 120637.097 530006.088 120637.251 530005.761 120637.738 530004.727 120638.271 530003.596 120638.435 530003.317 120639.006 530002.345 120639.773 530001.04 120640.197 530000.343 120640.406 530000.0 120647.85 529987.778 120671.69 529948.632 120671.878 529948.342 120672.494 529947.394 120710.878 529888.279 120718.619 529875.994 120721.43 529871.534 120722.936 529868.751 120723.75 529867.245 120724.253 529866.08 120725.684 529862.769 120726.542 529860.183 120727.219 529858.14 120727.618 529856.451 120728.341 529853.394 120728.729 529850.721 120729.042 529848.569 120729.317 529843.7 120729.164 529838.826 120728.583 529833.984 120728.418 529833.198 120727.58 529829.212 120726.549 529825.82 120726.162 529824.546 120725.195 529822.147 120724.339 529820.023 120722.127 529815.677 120721.652 529814.918 120719.542 529811.543 120716.604 529807.651 120713.336 529804.031 120709.763 529800.713 120707.666 529799.083 120705.912 529797.721 120703.769 529796.339 120701.814 529795.078 120683.032 529785.064 120666.717 529776.365 120662.164 529773.937 120633.337 529758.568 120622.288 529752.676 120615.725 529749.268 120609.286 529745.923 120607.224 529744.852 120606.693 529744.576 120604.606 529743.492 120584.372 529732.983 120572.972 529727.062 120567.509 529724.225 120546.476 529713.3 120544.189 529712.052 120513.022 529695.05 120498.499 529687.128 120480.229 529677.161 120479.558 529676.795 120443.535 529657.629 120440.606 529656.07 120423.294 529646.859 120414.431 529642.143 120407.521 529638.467 120382.799 529625.469 120376.461 529622.137 120367.829 529617.599 120345.415 529605.814 120343.58 529604.796 120329.551 529597.005 120325.962 529595.012 120306.499 529584.205 120306.187 529584.073 120303.193 529582.808 120300.535 529582.997 120299.818 529583.048 120299.209 529583.091 120298.885 529583.294 120297.63 529584.08 120296.629 529585.336 120296.172 529585.909 120296.321 529585.969 120296.398 529586.0 120296.438 529586.016 120296.493 529586.038 120296.542 529586.057 120296.608 529586.084 120296.65 529586.101 120296.673 529586.11 120296.703 529586.122 120295.362 529589.267 120294.872 529590.415 120294.296 529590.166 120294.265 529590.153 120294.035 529590.553 120293.703 529591.131 120294.026 529592.589 120294.663 529593.157 120295.317 529593.741 120296.629 529594.918 120296.778 529595.066 120297.789 529595.88 120298.383 529596.358 120298.799 529596.693 120298.907 529596.765 120298.954 529596.796 120311.71 529603.619 120319.198 529607.625 120336.8 529617.04 120356.972 529627.831 120369.763 529634.673 120374.645 529637.284 120393.134 529647.054 120416.597 529659.451 120422.258 529662.442 120436.9 529670.179 120449.977 529677.089 120458.544 529681.616 120491.891 529699.265 120506.644 529707.073 120511.031 529709.395 120525.24 529716.914 120561.384 529736.003 120566.807 529738.867 120578.118 529744.84 120582.694 529747.257 120593.543 529752.987 120596.257 529754.421 120597.522 529755.089 120626.744 529770.919 120655.397 529786.441 120655.965 529786.749 120665.78 529792.237 120676.106 529798.01 120684.28 529802.58 120696.154 529809.219 120698.864 529811.657 120700.579 529813.199 120703.856 529816.148 120704.502 529816.73 120704.935 529817.119 120705.197 529817.683 120706.735 529820.995 120710.077 529828.192 120710.488 529829.677 120711.687 529834.006 120713.282 529839.766 120713.261 529845.399 120713.261 529845.521 120713.26 529845.703 120713.246 529849.646 120713.239 529851.293 120713.233 529851.317 120712.81 529853.01 120712.524 529854.153 120712.351 529854.844 120709.052 529861.365 120707.955 529863.534 120706.778 529865.874 120703.505 529872.383 120695.037 529885.606 120688.767 529895.398 120685.209 529900.954 120679.023 529910.614 120674.906 529917.042 120674.002 529918.454 120660.394 529939.541 120646.774 529960.645 120645.82 529962.252 120642.897 529967.176 120641.615 529969.336 120635.241 529980.076 120628.493 529991.446 120626.444 529994.899 120626.149 529995.397 120624.394 529998.353 120623.374 529999.967 120623.353 530000.0 120623.291 530000.099 120619.78 530005.656 120618.518 530010.078 120617.975 530011.982 120616.749 530021.582 120616.63 530026.749 120616.59 530028.488 120617.939 530036.663 120622.622 530048.252 120627.623 530055.634 120632.543 530060.76 120636.308 530064.422 120636.686 530064.79 120636.769 530064.865 120641.546 530068.861 120641.646 530068.939 120648.49 530073.745 120650.334 530075.22 120659.933 530082.897 120666.201 530087.887 120671.585 530092.174 120690.643 530108.043 120694.279 530111.269 120697.844 530114.431 120717.239 530131.634 120721.021 530134.989 120814.788 530209.309 120818.461 530212.107 120820.849 530213.927 120850.643 530236.63 120857.577 530241.914 120870.796 530252.699 120870.818 530252.716 120870.858 530252.747 120877.095 530257.313 120879.678 530259.204 120888.45 530265.625 120890.993 530267.672 120901.28 530275.954 120918.222 530289.995 120924.816 530295.268 120930.383 530299.72 120933.438 530302.163 120934.719 530303.187 120937.026 530304.96 120944.215 530310.487 120953.676 530317.76 120963.66 530325.82 120963.863 530325.984 120966.741 530328.307 120969.17 530330.268 120973.673 530333.904 120979.452 530338.443 120985.26 530343.004 120986.225 530343.762 120995.645 530351.159 120999.251 530353.99 120999.92 530354.51 121000.0 530354.573 121000.202 530354.73 121000.738 530355.148 121007.437 530360.365 121013.377 530364.99 121016.099 530367.11 121020.829 530370.847 121024.154 530373.474 121027.203 530375.884 121028.528 530376.931 121029.855 530377.979 121040.949 530386.745 121050.252 530394.38 121051.993 530395.808 121056.929 530399.859 121063.043 530404.876 121064.492 530406.093 121065.093 530406.598 121065.829 530407.216 121067.142 530408.319 121068.058 530409.062 121092.619 530428.975 121093.171 530429.422 121093.191 530429.438 121094.108 530430.182 121102.295 530436.78 121107.256 530440.778 121108.856 530443.171 121109.591 530444.269 121109.809 530444.025 121103.509 530390.926 121103.258 530390.734</gml:posList>
                        </gml:LinearRing>
                     </gml:exterior>
                  </gml:Polygon>
               </gml:surfaceMember>
            </gml:MultiSurface>
         </basisgeo:geometrie>
      </basisgeo:Geometrie>
   </basisgeo:featureMember>
</basisgeo:FeatureCollectionGeometrie>
