<?xml version="1.0" encoding="utf-8"?>
<AanleveringInformatieObject xmlns="https://standaarden.overheid.nl/lvbb/stop/aanlevering/"
                             schemaversie="1.0.3">
   <InformatieObjectVersie>
      <ExpressionIdentificatie xmlns="https://standaarden.overheid.nl/stop/imop/data/">
         <FRBRWork>/join/id/regdata/pv26/2020/dempenoppervlaktewaterlichamen</FRBRWork>
         <FRBRExpression>/join/id/regdata/pv26/2020/dempenoppervlaktewaterlichamen/nld@2020-06-02</FRBRExpression>
         <soortWork>/join/id/stop/work_007</soortWork>
      </ExpressionIdentificatie>
      <InformatieObjectVersieMetadata xmlns="https://standaarden.overheid.nl/stop/imop/data/">
         <heeftGeboorteregeling>/akn/nl/act/pv26/2020/OVPU001</heeftGeboorteregeling>
         <heeftBestanden>
            <heeftBestand>
               <Bestand>
                  <bestandsnaam>Dempenoppervlaktewaterlichamen.gml</bestandsnaam>
                  <hash>a16f0a6a5edc093e1e63c1c2a9c870e4a28a6c0b1919730a3c3293070b146fd6347fed680583c3271b05bbaf7a7e7923e2f0916a86e5c960eb7e863df28e162b</hash>
               </Bestand>
            </heeftBestand>
         </heeftBestanden>
      </InformatieObjectVersieMetadata>
      <InformatieObjectMetadata xmlns="https://standaarden.overheid.nl/stop/imop/data/">
         <eindverantwoordelijke>/tooi/id/provincie/pv26</eindverantwoordelijke>
         <maker>/tooi/id/provincie/pv26</maker>
         <alternatieveTitels>
            <alternatieveTitel>Dempen oppervlaktewaterlichamen</alternatieveTitel>
         </alternatieveTitels>
         <officieleTitel>/join/id/regdata/pv26/2020/dempenoppervlaktewaterlichamen/nld@2020-06-02</officieleTitel>
         <publicatieinstructie>TeConsolideren</publicatieinstructie>
         <naamInformatieObject>Dempen oppervlaktewaterlichamen</naamInformatieObject>
         <formaatInformatieobject>/join/id/stop/informatieobject/gio_002</formaatInformatieobject>
      </InformatieObjectMetadata>
   </InformatieObjectVersie>
</AanleveringInformatieObject>
