<?xml version="1.0" encoding="UTF-8"?>
<basisgeo:FeatureCollectionGeometrie xmlns:basisgeo="http://www.geostandaarden.nl/basisgeometrie/1.0"
                                     xmlns:gml="http://www.opengis.net/gml/3.2">
   <basisgeo:featureMember>
      <basisgeo:Geometrie xmlns:geo="https://standaarden.overheid.nl/stop/imop/geo/"
                          xmlns:gio="https://standaarden.overheid.nl/stop/imop/gio/"
                          gml:id="id-8ef44035-e242-4e4c-99c3-3b977692e31d-xx">
         <basisgeo:id>8ef44035-e242-4e4c-99c3-3b977692e31d</basisgeo:id>
         <basisgeo:geometrie>
            <gml:MultiSurface srsName="urn:ogc:def:crs:EPSG::28992"
                              gml:id="id-8ef44035-e242-4e4c-99c3-3b977692e31d">
               <gml:surfaceMember>
                  <gml:Polygon>
                     <gml:exterior>
                        <gml:LinearRing>
                           <gml:posList>110482.299 414652.853 110505.051 414636.948 110524.04 414625.44 110535.753 414618.342 110539.567 414616.842 110547.617 414613.676 110550.771 414612.761 110553.786 414611.886 110555.44 414611.716 110556.637 414611.593 110558.64 414611.637 110579.411 414615.398 110605.927 414621.408 110642.691 414629.547 110643.717 414629.774 110646.462 414630.195 110658.995 414632.118 110681.227 414634.425 110701.781 414635.913 110734.37 414636.107 110757.148 414635.918 110780.018 414636.155 110782.883 414636.185 110787.754 414637.096 110789.453 414637.533 110791.018 414638.068 110792.82 414638.241 110793.097 414638.274 110795.331 414638.541 110807.94 414641.23 110818.268 414638.676 110818.736 414638.56 110821.443 414637.95 110822.315 414637.636 110822.773 414637.471 110846.823 414624.343 110849.472 414623.018 110850.757 414622.375 110854.207 414621.859 110861.914 414619.909 110865.982 414617.81 110880.28 414610.78 110893.737 414603.589 110911.235 414593.735 110916.492 414590.775 110916.734 414590.734 110917.222 414590.653 110917.413 414590.655 110917.917 414590.662 110926.001 414586.296 110926.133 414587.854 110926.201 414588.653 110927.266 414587.906 110927.471 414587.762 110927.767 414586.438 110927.781 414586.375 110928.668 414585.142 110929.058 414584.878 110930.994 414583.571 110933.625 414583.043 110936.715 414582.981 110937.569 414582.899 110938.483 414582.811 110941.834 414581.214 110961.144 414568.517 110981.738 414552.656 110989.306 414546.23 111002.481 414535.044 111027.909 414514.289 111029.857 414512.699 111050.442 414494.964 111057.479 414488.902 111078.061 414470.792 111112.649 414438.463 111129.31 414422.84 111149.218 414400.842 111159.845 414387.636 111174.248 414369.737 111195.438 414343.037 111217.541 414315.963 111237.438 414287.981 111244.69 414277.923 111250.472 414269.904 111257.534 414258.466 111257.901 414257.871 111260.423 414253.824 111277.601 414226.252 111279.933 414222.891 111299.497 414194.697 111312.765 414176.389 111316.833 414169.744 111325.242 414156.01 111334.93 414138.968 111335.094 414138.826 111335.213 414138.722 111335.59 414138.133 111335.79 414137.822 111336.919 414136.585 111338.749 414134.579 111339.685 414133.553 111339.729 414133.505 111341.143 414129.889 111350.015 414107.192 111357.362 414080.586 111357.8 414079.001 111362.599 414066.454 111366.111 414057.502 111370.47 414049.836 111373.809 414043.965 111377.916 414037.207 111384.492 414026.387 111393.753 414013.901 111404.885 414000.725 111409.581 413996.457 111418.107 413988.708 111427.633 413978.629 111431.378 413974.666 111431.462 413973.682 111431.589 413972.208 111431.938 413968.165 111432.124 413966.002 111431.973 413965.611 111431.893 413965.402 111431.902 413964.696 111432.01 413964.098 111432.096 413963.627 111438.89 413949.53 111440.662 413946.97 111445.058 413940.621 111448.659 413935.481 111450.082 413931.628 111454.502 413919.656 111454.916 413918.972 111455.22 413918.719 111455.838 413918.205 111463.456 413912.352 111470.32 413907.079 111476.922 413903.51 111478.154 413902.377 111481.542 413899.264 111483.961 413896.951 111490.892 413892.45 111498.55 413887.476 111520.835 413871.473 111525.996 413867.767 111544.454 413849.142 111554.456 413839.537 111562.96 413831.371 111580.072 413818.465 111586.774 413813.824 111601.732 413803.465 111611.533 413797.413 111628.818 413786.741 111632.115 413785.895 111633.142 413785.691 111633.944 413785.472 111634.444 413785.454 111634.847 413785.44 111636.094 413785.656 111637.206 413786.223 111638.181 413786.826 111639.034 413787.219 111641.496 413787.445 111642.046 413787.3 111642.623 413787.089 111642.738 413786.996 111643.241 413786.588 111645.272 413784.76 111655.705 413778.72 111688.097 413756.168 111773.163 413701.425 111814.955 413675.244 111838.703 413660.793 111849.829 413654.023 111855.982 413650.717 111872.175 413642.016 111874.151 413641.062 111883.428 413637.998 111889.958 413635.842 111891.616 413635.611 111892.921 413635.608 111893.666 413635.607 111895.768 413635.743 111895.976 413635.756 111900.901 413626.149 111900.469 413625.402 111900.396 413625.089 111900.247 413624.451 111900.246 413623.983 111900.246 413623.797 111902.306 413619.146 111906.008 413610.787 111906.063 413610.681 111906.182 413610.449 111906.539 413609.993 111923.829 413602.41 111969.419 413580.365 111967.916 413577.166 111966.139 413573.465 111948.078 413581.85 111931.013 413589.802 111921.859 413594.067 111902.871 413603.655 111902.747 413603.692 111902.449 413603.78 111901.665 413603.773 111901.532 413603.764 111900.775 413603.716 111899.864 413604.717 111897.918 413606.855 111896.577 413608.328 111895.904 413611.008 111893.449 413616.279 111892.465 413618.393 111890.8 413620.552 111890.76 413620.599 111889.598 413621.957 111885.76 413623.972 111885.493 413624.112 111878.946 413627.024 111844.998 413642.122 111816.156 413656.154 111813.132 413657.822 111784.908 413673.386 111784.282 413673.379 111784.08 413673.377 111783.223 413673.147 111782.754 413672.943 111782.163 413672.687 111781.362 413672.613 111779.655 413673.772 111757.047 413689.115 111743.385 413697.158 111723.342 413708.958 111712.569 413717.786 111711.655 413718.535 111711.346 413718.697 111704.595 413722.244 111687.588 413730.847 111686.377 413731.849 111679.646 413737.419 111674.743 413740.604 111666.887 413745.707 111650.75 413755.971 111632.598 413767.517 111601.48 413788.136 111580.611 413802.792 111577.857 413804.726 111577.399 413805.094 111552.623 413825.004 111535.669 413840.912 111534.025 413839.368 111533.362 413839.173 111526.269 413844.753 111506.204 413858.799 111500.041 413863.386 111486.615 413873.377 111466.121 413891.486 111437.126 413917.825 111408.446 413946.033 111397.103 413959.772 111392.72 413963.663 111383.282 413972.042 111369.148 413986.925 111360.333 413996.206 111342.159 414016.955 111338.658 414021.453 111329.894 414032.713 111318.556 414049.028 111314.167 414055.345 111313.678 414056.157 111313.09 414057.348 111312.639 414058.47 111307.946 414078.117 111307.549 414080.214 111307.269 414081.696 111306.768 414082.792 111306.563 414083.239 111305.829 414084.219 111305.372 414084.464 111304.505 414084.929 111302.951 414085.602 111302.55 414086.257 111302.286 414096.983 111302.118 414097.275 111301.851 414097.737 111301.797 414097.775 111300.922 414098.385 111298.68 414098.686 111297.707 414098.892 111297.063 414099.028 111296.365 414099.778 111295.86 414100.927 111295.88 414101.153 111295.98 414102.249 111297.763 414109.408 111299.948 414118.18 111299.936 414119.501 111299.65 414120.082 111299.5 414120.387 111299.262 414120.571 111298.239 414121.361 111296.871 414122.264 111293.335 414124.598 111185.926 414279.096 111185.851 414280.085 111186.403 414280.984 111191.039 414286.135 111193.378 414288.734 111193.57 414289.397 111193.497 414290.122 111192.962 414291.039 111192.2 414291.525 111191.211 414291.578 111190.365 414291.314 111189.996 414291.199 111183.472 414288.044 111182.388 414287.733 111181.996 414287.806 111181.399 414287.918 111180.603 414288.502 111178.568 414291.227 111171.666 414300.469 111170.764 414300.966 111170.143 414301.308 111168.851 414302.116 111167.981 414303.69 111168.008 414303.91 111168.103 414304.682 111168.871 414305.629 111169.699 414306.65 111174.021 414309.347 111174.166 414309.686 111174.375 414310.177 111174.3 414311.167 111174.12 414311.504 111173.864 414311.986 111170.397 414315.494 111161.005 414324.996 111131.656 414358.605 111110.204 414382.886 111070.565 414427.754 111065.876 414432.321 111064.716 414433.451 111062.778 414434.267 111061.555 414434.51 111061.115 414434.597 111058.696 414435.003 111058.432 414435.013 111055.982 414435.109 111055.57 414435.194 111053.696 414435.582 111035.165 414450.421 111032.632 414452.587 111012.035 414471.716 111003.473 414479.668 111000.329 414482.361 110999.458 414483.107 110969.105 414510.444 110968.628 414510.834 110964.888 414513.896 110962.55 414515.055 110958.325 414517.15 110935.102 414526.432 110933.762 414527.261 110933.634 414527.339 110933.393 414528.032 110933.442 414529.225 110933.454 414529.275 110933.881 414531.02 110933.768 414535.116 110933.683 414538.206 110933.026 414542.636 110932.075 414545.282 110931.581 414546.658 110929.921 414549.45 110928.439 414551.351 110926.357 414553.248 110925.323 414554.19 110920.978 414557.309 110893.761 414573.161 110892.784 414574.112 110892.117 414574.761 110886.309 414580.875 110866.88 414595.809 110861.777 414598.752 110858.051 414600.224 110854.733 414600.906 110851.923 414601.052 110848.706 414601.219 110833.837 414601.384 110828.884 414601.439 110822.25 414602.671 110818.316 414603.584 110807.18 414606.17 110804.008 414609.052 110801.183 414611.619 110798.565 414611.88 110797.961 414611.88 110796.282 414611.881 110793.941 414611.285 110792.07 414610.232 110790.527 414609.316 110789.147 414608.611 110788.326 414608.192 110787.716 414608.025 110786.282 414607.633 110765.89 414606.056 110761.863 414605.337 110759.11 414604.695 110757.832 414604.397 110753.848 414603.469 110751.104 414603.331 110749.166 414603.443 110746.965 414603.571 110734.301 414603.147 110712.967 414602.432 110698.135 414600.635 110695.659 414600.335 110687.447 414598.994 110673.012 414596.638 110652.983 414592.681 110632.093 414588.777 110629.986 414588.505 110624.331 414587.774 110622.197 414586.903 110617.521 414584.995 110612.029 414582.566 110608.664 414579.438 110605.451 414577.466 110604.649 414576.974 110598.001 414572.895 110597.122 414572.067 110595.715 414570.743 110593.627 414567.631 110592.797 414566.395 110592.59 414565.627 110591.947 414563.236 110591.609 414560.773 110591.496 414559.95 110590.303 414557.714 110589.822 414557.423 110589.756 414557.383 110589.681 414557.338 110588.564 414556.662 110584.417 414555.014 110569.818 414553.219 110567.215 414552.421 110563.89 414551.215 110553.134 414551.114 110548.208 414551.068 110547.232 414551.255 110543.489 414551.273 110542.596 414551.237 110542.031 414551.214 110535.603 414549.952 110532.068 414549.258 110515.126 414549.49 110501.569 414551.03 110498.091 414552.376 110496.061 414553.161 110481.379 414559.927 110463.985 414567.854 110457.339 414570.882 110433.496 414581.57 110402.59 414598.391 110399.63 414600.24 110377.1 414614.312 110374.34 414614.912 110337.311 414564.627 110335.968 414565.616 110334.594 414566.609 110355.9 414596.072 110370.761 414616.624 110372.09 414618.462 110381.7 414625.93 110386.572 414631.683 110397.18 414644.211 110402.23 414642.77 110404.4 414642.151 110407.616 414644.883 110409.19 414646.221 110412.05 414655.801 110425.27 414649.551 110428.021 414648.813 110428.849 414648.71 110431.709 414648.964 110432.032 414648.993 110433.905 414649.066 110434.261 414649.091 110435.231 414649.159 110437.204 414649.747 110438.904 414650.254 110439.322 414650.832 110440.087 414651.426 110441.101 414651.935 110442.879 414652.573 110443.431 414653.057 110443.745 414653.331 110445.148 414655.414 110445.719 414657.069 110445.991 414658.295 110446.062 414659.389 110445.737 414660.651 110445.358 414661.207 110444.864 414661.932 110443.693 414663.248 110437.615 414668.119 110428.025 414675.626 110427.595 414675.962 110427.34 414676.162 110427.384 414676.224 110429.023 414678.513 110429.075 414678.478 110429.324 414678.311 110432.445 414682.966 110432.44 414682.97 110432.288 414683.072 110432.693 414683.637 110433.517 414684.788 110433.818 414684.606 110436.612 414682.916 110442.164 414679.556 110463.654 414665.887 110482.299 414652.853</gml:posList>
                        </gml:LinearRing>
                     </gml:exterior>
                  </gml:Polygon>
               </gml:surfaceMember>
            </gml:MultiSurface>
         </basisgeo:geometrie>
      </basisgeo:Geometrie>
   </basisgeo:featureMember>
</basisgeo:FeatureCollectionGeometrie>
