<?xml version="1.0" encoding="utf-8"?>
<AanleveringGIO xmlns="https://standaarden.overheid.nl/lvbb/stop/"
                xmlns:gml="http://www.opengis.net/gml/3.2"
                xmlns:geo="https://standaarden.overheid.nl/stop/imop/geo/"
                xmlns:xlink="http://www.w3.org/1999/xlink"
                schemaversie="0.98.3-kern">
   <InformatieObjectVersie>
      <ExpressionIdentificatie xmlns="https://standaarden.overheid.nl/stop/imop/data/">
         <FRBRWork>/join/id/regdata/pv26/2020/militairerfgoed</FRBRWork>
         <FRBRExpression>/join/id/regdata/pv26/2020/militairerfgoed/nld@2020-06-02</FRBRExpression>
         <soortWork>/join/id/stop/work_007</soortWork>
      </ExpressionIdentificatie>
      <InformatieObjectMetadata xmlns="https://standaarden.overheid.nl/stop/imop/data/">
         <eindverantwoordelijke>/tooi/id/provincie/pv26</eindverantwoordelijke>
         <maker>/tooi/id/provincie/pv26</maker>
         <noemer>Militair erfgoed</noemer>
         <officieleTitel>/join/id/regdata/pv26/2020/militairerfgoed/nld@2020-06-02</officieleTitel>
         <publicatieinstructie>TeConsolideren</publicatieinstructie>
         <soortInformatieobject>/join/id/stop/informatieobject/gio_001</soortInformatieobject>
         <!-- Koppeling naar het gml-bestand -->
         <heeftBestanden>
            <heeftBestand>
               <Bestand>
                  <bestandsnaam>CHS-militairerfgoed.gml</bestandsnaam>
                  <hash>d3239fc75a14e167242818da31210a07c4ff20d2ce589359bb999899bdbf6d826a05caef692d2bd70f47be6394a1d1c221ce24cc645b986f98b67c653d172e7f</hash>
               </Bestand>
            </heeftBestand>
         </heeftBestanden>
      </InformatieObjectMetadata>
      <GeoInformatie xmlns="https://standaarden.overheid.nl/stop/imop/geo/"
                     gml:id="dad411de9-4561-4aec-bae5-b763a116a5f6">
         <geo:featureMember>
            <geo:Locatie gml:id="tad411de9-4561-4aec-bae5-b763a116a5f6">
               <geo:wId>tad411de9-4561-4aec-bae5-b763a116a5f6</geo:wId>
               <geo:naam>Militair erfgoed</geo:naam>
               <geo:geometrie xlink:href="CHS-militairerfgoed.gml#tad411de9-4561-4aec-bae5-b763a116a5f6"/>
            </geo:Locatie>
         </geo:featureMember>
      </GeoInformatie>
      <Achtergrond xmlns="https://standaarden.overheid.nl/stop/imop/data/">
         <bronactualiteit>2019-01-01</bronactualiteit>
         <bronbeschrijving>TOP10NL</bronbeschrijving>
         <brontype>achtergrond</brontype>
      </Achtergrond>
   </InformatieObjectVersie>
</AanleveringGIO>
